LICENCE
README.md
setup.py
vpo/__init__.py
vpo/authkey.py
vpo/disc.py
vpo/others.py
vpo.egg-info/PKG-INFO
vpo.egg-info/SOURCES.txt
vpo.egg-info/dependency_links.txt
vpo.egg-info/requires.txt
vpo.egg-info/top_level.txt