Metadata-Version: 2.1
Name: vpo
Version: 2.0
Summary: Un package qui vous facilitera la vie: un système de keyauth automatique par exemple
Home-page: https://github.com/hackiyui/vpimport
Author: VP_Services
Author-email: discordyashing@gmail.com
Classifier: Environment :: Win32 (MS Windows)
Classifier: Natural Language :: French
Classifier: Operating System :: Microsoft :: Windows :: Windows 10
Classifier: Operating System :: Microsoft :: Windows :: Windows 11
Classifier: Programming Language :: Python :: 3.11
Classifier: Topic :: Internet :: Proxy Servers
Classifier: Topic :: System
Classifier: Topic :: System :: Logging
Requires-Python: >=3.11
License-File: LICENCE
